.DS_Store
django_sohoui/__init__.py
django_sohoui/admin.py
django_sohoui/adminsite.py
django_sohoui/apps.py
django_sohoui/context_processors.py
django_sohoui/fields.py
django_sohoui/forms.py
django_sohoui/models.py
django_sohoui/urls.py
django_sohoui/views.py
django_sohoui/widgets.py
django_sohoui/migrations/__init__.py
django_sohoui/static/django_sohoui/change_results.js
django_sohoui/static/django_sohoui/css/bootstrap.min.css
django_sohoui/static/django_sohoui/css/index.css
django_sohoui/static/django_sohoui/css/index_chalk.css
django_sohoui/static/django_sohoui/css/style.css
django_sohoui/static/django_sohoui/css/fonts/element-icons.ttf
django_sohoui/static/django_sohoui/css/fonts/element-icons.woff
django_sohoui/static/django_sohoui/elementUI/css/index.css
django_sohoui/static/django_sohoui/elementUI/fonts/element-icons.ttf
django_sohoui/static/django_sohoui/elementUI/fonts/element-icons.woff
django_sohoui/static/django_sohoui/elementUI/js/index.js
django_sohoui/static/django_sohoui/elementUI/js/vue.js
django_sohoui/static/django_sohoui/images/logo_bg.jpg
django_sohoui/static/django_sohoui/js/Sortable.min.js
django_sohoui/static/django_sohoui/js/axios.min.js
django_sohoui/static/django_sohoui/js/b1.jpg
django_sohoui/static/django_sohoui/js/bootstrap.bundle.min.js
django_sohoui/static/django_sohoui/js/bootstrap.min.css
django_sohoui/static/django_sohoui/js/index.js
django_sohoui/static/django_sohoui/js/inlines.js
django_sohoui/static/django_sohoui/js/jquery.min.js
django_sohoui/static/django_sohoui/js/vue.js
django_sohoui/static/django_sohoui/typescript/css/dashboard.css
django_sohoui/static/django_sohoui/typescript/js/app_list.js
django_sohoui/static/django_sohoui/typescript/js/base.js
django_sohoui/static/django_sohoui/typescript/js/change_form.js
django_sohoui/static/django_sohoui/typescript/js/change_list.js
django_sohoui/static/django_sohoui/typescript/js/dashboard.js
django_sohoui/static/django_sohoui/typescript/js/widgets.js
django_sohoui-1.3.9.dist-info/LICENSE
django_sohoui-1.3.9.dist-info/METADATA
django_sohoui-1.3.9.dist-info/WHEEL
django_sohoui-1.3.9.dist-info/top_level.txt
django_sohoui-1.3.9.dist-info/RECORD
