Metadata-Version: 2.1
Name: django_sohoui
Version: 1.3.9
Summary: django soho ui base
Home-page: https://github.com/liuzhimin2019/django_sohoui.git
Author: zack_liu
Author-email: liu.zhimin.2019@gmail.com
Classifier: Programming Language :: Python :: 3
Classifier: License :: OSI Approved :: MIT License
Classifier: Operating System :: OS Independent
Requires-Python: >=3
License-File: LICENSE
Requires-Dist: django==4.2.21
